agora/__init__.py
agora/abc.py
agora/io/__init__.py
agora/io/bridge.py
agora/io/cells.py
agora/io/decorators.py
agora/io/metadata.py
agora/io/reader.py
agora/io/signal.py
agora/io/utils.py
agora/io/writer.py
agora/logging.py
agora/track_abc.py
agora/utils/__init__.py
agora/utils/association.py
agora/utils/cast.py
agora/utils/indexing.py
agora/utils/kymograph.py
agora/utils/lineage.py
agora/utils/merge.py
aliby/__init__.py
aliby/baby_client.py
aliby/bin/2023_03_20_annotation/annotation.csv
aliby/bin/__init__.py
aliby/bin/annotate.py
aliby/bin/run.py
aliby/haystack.py
aliby/io/__init__.py
aliby/io/dataset.py
aliby/io/image.py
aliby/io/omero.py
aliby/lineage/__init__.py
aliby/lineage/bud_tracker.py
aliby/pipeline.py
aliby/tile/__init__.py
aliby/tile/tiler.py
aliby/tile/traps.py
aliby/track/__init__.py
aliby/track/benchmark.py
aliby/track/cell_tracker.py
aliby/track/utils.py
aliby/utils/__init__.py
aliby/utils/argo.py
aliby/utils/imageViewer.py
aliby/utils/plot.py
aliby/utils/vis_tools.py
extraction/__init__.py
extraction/core/__init__.py
extraction/core/extractor.py
extraction/core/functions/__init__.py
extraction/core/functions/cell.py
extraction/core/functions/custom/__init__.py
extraction/core/functions/custom/localisation.py
extraction/core/functions/defaults.py
extraction/core/functions/distributors.py
extraction/core/functions/loaders.py
extraction/core/functions/math_utils.py
extraction/core/functions/trap.py
extraction/core/functions/versioning.py
extraction/local_data_loaders.py
logfile_parser/README.md
logfile_parser/__init__.py
logfile_parser/grammars/cExperiment_log_format.json
logfile_parser/grammars/multiDGUI_acq_format.json
logfile_parser/grammars/multiDGUI_log_format.json
logfile_parser/legacy.py
logfile_parser/logfile_parser.py
logfile_parser/swainlab_parser.py
postprocessor/__init__.py
postprocessor/chainer.py
postprocessor/compiler.py
postprocessor/core/__init__.py
postprocessor/core/abc.py
postprocessor/core/functions/__init__.py
aliby-0.1.64.dist-info/WHEEL
aliby-0.1.64.dist-info/entry_points.txt
aliby-0.1.64.dist-info/LICENSE
aliby-0.1.64.dist-info/METADATA
aliby-0.1.64.dist-info/RECORD
