Metadata-Version: 2.1
Name: aliby
Version: 0.1.64
Summary: Process and analyse live-cell imaging data
Author: Alan Munoz
Author-email: alan.munoz@ed.ac.uk
Requires-Python: >=3.8,<3.11
Classifier: Programming Language :: Python :: 3
Classifier: Programming Language :: Python :: 3.8
Classifier: Programming Language :: Python :: 3.9
Classifier: Programming Language :: Python :: 3.10
Provides-Extra: baby
Provides-Extra: omero
Requires-Dist: Bottleneck (>=1.3.5,<2.0.0)
Requires-Dist: GitPython (>=3.1.27,<4.0.0)
Requires-Dist: PyYAML (>=6.0,<7.0)
Requires-Dist: aliby-baby (>=0.1.17,<0.2.0) ; extra == "baby"
Requires-Dist: dask (>=2021.12.0,<2022.0.0)
Requires-Dist: flatten-dict (>=0.4.2,<0.5.0)
Requires-Dist: gaussianprocessderivatives (>=0.1.5,<0.2.0)
Requires-Dist: h5py (==2.10)
Requires-Dist: imageio (==2.8.0)
Requires-Dist: numpy (>=1.21.6)
Requires-Dist: omero-py (>=5.6.2) ; extra == "omero"
Requires-Dist: opencv-python (>=4.7.0.72,<5.0.0.0)
Requires-Dist: p-tqdm (>=1.3.3,<2.0.0)
Requires-Dist: pandas (>=1.3.3)
Requires-Dist: pathos (>=0.2.8,<0.3.0)
Requires-Dist: py-find-1st (>=1.1.5,<2.0.0)
Requires-Dist: requests-toolbelt (>=0.9.1,<0.10.0)
Requires-Dist: scikit-image (>=0.18.1)
Requires-Dist: scikit-learn (>=1.0.2)
Requires-Dist: scipy (>=1.7.3)
Requires-Dist: tqdm (>=4.62.3,<5.0.0)
Requires-Dist: xmltodict (>=0.13.0,<0.14.0)
Requires-Dist: zarr (>=2.14.0,<3.0.0)
